slapimage/__init__.py
slapimage/constants/const.mp
slapimage/draw.py
slapimage-0.0.0.0a0.dist-info/METADATA
slapimage-0.0.0.0a0.dist-info/WHEEL
slapimage-0.0.0.0a0.dist-info/RECORD
