Metadata-Version: 2.1
Name: slapimage
Version: 0.0.0.0a0
Summary: This is for our family business. DON'T YOU DARE USE THIS!
Home-page: https://slapimg.whinyaan.xyz
License: MIT
Keywords: your,keywords,here
Author: Lyra
Author-email: whinyaan@protonmail.com
Maintainer: Lyra
Maintainer-email: whinyaan@protonmail.com
Requires-Python: >=3.10,<4
Classifier: Development Status :: 2 - Pre-Alpha
Classifier: Environment :: Console
Classifier: Intended Audience :: Developers
Classifier: License :: OSI Approved :: MIT License
Classifier: Natural Language :: English
Classifier: Operating System :: OS Independent
Classifier: Programming Language :: Python :: 3
Classifier: Programming Language :: Python :: 3.10
Classifier: Programming Language :: Python :: 3.11
Classifier: Topic :: Utilities
Requires-Dist: arrow (>=1.2.3,<2.0.0)
Requires-Dist: httpx (>=0.24.0,<0.25.0)
Requires-Dist: msgpack (>=1.0.5,<2.0.0)
Requires-Dist: openpyxl (>=3.1.2,<4.0.0)
Requires-Dist: pillow (>=10.0.0,<11.0.0)
Requires-Dist: pyyaml (>=6.0,<7.0)
Requires-Dist: toml (>=0.10.2,<0.11.0)
Requires-Dist: whinesnips (==0.0.0.0a3)
Project-URL: Documentation, https://slapimg.whinyaan.xyz
Project-URL: Repository, https://github.com/whinee/slapimage
